wikiWrapper/__init__.py
wikiWrapper/wikiWrapper.py
wikiWrapper-0.0.1a0.dist-info/LICENSE
wikiWrapper-0.0.1a0.dist-info/METADATA
wikiWrapper-0.0.1a0.dist-info/WHEEL
wikiWrapper-0.0.1a0.dist-info/top_level.txt
wikiWrapper-0.0.1a0.dist-info/RECORD
