Metadata-Version: 2.1
Name: wikiWrapper
Version: 0.0.1a0
Summary: A few helpful classes for working with mediawiki data
Home-page: https://github.com/git-shr4pnel/wikiWrapper
Author: Tyler D.
Author-email: shr4p.apis@gmail.com
License: UNKNOWN
Platform: UNKNOWN
Classifier: Programming Language :: Python :: 3
Classifier: License :: OSI Approved :: MIT License
Classifier: Operating System :: OS Independent
Requires-Python: >=3.7
License-File: LICENSE
